scapy_cdp/__init__.py
scapy_cdp/cdp.py
scapy_cdp/cdp_sender.py
scapy_cdp-0.1.0.dist-info/METADATA
scapy_cdp-0.1.0.dist-info/WHEEL
scapy_cdp-0.1.0.dist-info/entry_points.txt
scapy_cdp-0.1.0.dist-info/top_level.txt
scapy_cdp-0.1.0.dist-info/RECORD
