Metadata-Version: 2.4
Name: scapy-cdp
Version: 0.1.0
Summary: Send Cisco Discovery Protocol packets with Scapy
Author: CDP Maintainers
License: MIT
Requires-Python: >=3.8
Requires-Dist: scapy
